[
  {
    "id": "k4m2x8n1",
    "name": "Sofía",
    "gender": "female",
    "birthYear": 1998,
    "zodiacSign": "♍ Virgo (August 24 - September 22)",
    "activity": "works",
    "detail": "Graphic designer at a studio",
    "howWeMet": "Through a mutual friend at a gallery opening",
    "birthdayAlreadyHappened": false,
    "events": [
      {
        "id": "e1a27b3c",
        "date": "2021.04.10",
        "place": "Her place",
        "situation": "First date that turned into more",
        "score": 3,
        "details": "",
        "observations": ""
      },
      {
        "id": "f2b38c4d",
        "date": "2021.05.03",
        "place": "My place",
        "situation": "Movie night",
        "score": 4,
        "details": "She brought wine. We didn't actually watch the movie.",
        "observations": ""
      },
      {
        "id": "a3c49d5e",
        "date": "2021.07.15",
        "place": "Rooftop bar",
        "situation": "Night out",
        "score": 3,
        "details": "",
        "observations": "She seemed distracted. Something felt different that night."
      },
      {
        "id": "b4d50e6f",
        "date": "2021.09.01",
        "place": "Her place",
        "situation": "Her birthday gathering",
        "score": 4,
        "details": "Small group of friends. I was the last to leave.",
        "observations": ""
      },
      {
        "id": "c5e61f7a",
        "date": "2024.02.14",
        "place": "Bar downtown",
        "situation": "Ran into her by chance",
        "score": 2,
        "details": "",
        "observations": "Hadn't seen her in almost three years. Felt nostalgic more than anything."
      }
    ]
  },
  {
    "id": "p7r3t5q9",
    "name": "Jake",
    "gender": "male",
    "birthYear": 1997,
    "zodiacSign": "♏ Scorpio (October 23 - November 21)",
    "activity": "works",
    "detail": "Freelance photographer",
    "howWeMet": "Through a mutual friend, ended up at the same New Year's party",
    "birthdayAlreadyHappened": false,
    "events": [
      {
        "id": "d6e72f8b",
        "date": "2021.12.31",
        "place": "Rooftop NYE party",
        "situation": "New Year's Eve",
        "score": 2,
        "details": "",
        "observations": "Never saw him again after that night."
      }
    ]
  },
  {
    "id": "b8w6z1y4",
    "name": "Mia",
    "gender": "female",
    "birthYear": 2000,
    "zodiacSign": "♉ Taurus (April 20 - May 20)",
    "activity": "studies",
    "detail": "Architecture — second year",
    "howWeMet": "University, same faculty",
    "birthdayAlreadyHappened": true,
    "events": [
      {
        "id": "g7f83a9b",
        "date": "2021.10.15",
        "place": "University party",
        "situation": "End of semester celebration",
        "score": 3,
        "details": "",
        "observations": ""
      },
      {
        "id": "h8a94b0c",
        "date": "2021.11.20",
        "place": "House party",
        "situation": "House party",
        "score": 3,
        "details": "Ran into her there. It happened again almost by itself.",
        "observations": ""
      },
      {
        "id": "i9b05c1d",
        "date": "2021.12.05",
        "place": "Park bench at night",
        "situation": "Study break that went off track",
        "score": 4,
        "details": "",
        "observations": "Then exams came and we drifted. That's just how it went."
      }
    ]
  },
  {
    "id": "h2j9d5s7",
    "name": "Camille",
    "gender": "female",
    "birthYear": 1999,
    "zodiacSign": "♈ Aries (March 21 - April 19)",
    "activity": "works",
    "detail": "Marketing coordinator",
    "howWeMet": "New Year's Eve party, introduced by a mutual friend",
    "birthdayAlreadyHappened": true,
    "events": [
      {
        "id": "j0c16d2e",
        "date": "2020.12.31",
        "place": "Friend's apartment",
        "situation": "New Year's Eve",
        "score": 3,
        "details": "We'd just met that same night. The countdown did the rest.",
        "observations": ""
      },
      {
        "id": "k1d27e3f",
        "date": "2021.02.14",
        "place": "Bar",
        "situation": "Valentine's drinks",
        "score": 4,
        "details": "",
        "observations": ""
      },
      {
        "id": "l2e38f4a",
        "date": "2021.05.28",
        "place": "Park",
        "situation": "Slow afternoon walk",
        "score": 4,
        "details": "Late spring, the light was perfect. No real plan.",
        "observations": ""
      },
      {
        "id": "m3f49a5b",
        "date": "2021.08.20",
        "place": "Club",
        "situation": "Night out",
        "score": 2,
        "details": "",
        "observations": "It felt forced. We both knew something was shifting."
      },
      {
        "id": "n4a50b6c",
        "date": "2022.01.08",
        "place": "Her place",
        "situation": "Catching up after the holidays",
        "score": 3,
        "details": "",
        "observations": ""
      },
      {
        "id": "o5b61c7d",
        "date": "2022.04.02",
        "place": "My place",
        "situation": "She came over, nothing planned",
        "score": 4,
        "details": "",
        "observations": ""
      },
      {
        "id": "p6c72d8e",
        "date": "2023.06.17",
        "place": "Beach bar",
        "situation": "Reconnected after months of silence",
        "score": 3,
        "details": "",
        "observations": "She texted out of nowhere. Some things don't expire."
      }
    ]
  },
  {
    "id": "n6v1c3g8",
    "name": "Tom",
    "gender": "male",
    "birthYear": 1996,
    "zodiacSign": "♌ Leo (July 23 - August 23)",
    "activity": "works",
    "detail": "Sound engineer",
    "howWeMet": "At a music festival, we ended up near the same stage",
    "birthdayAlreadyHappened": false,
    "events": [
      {
        "id": "q7d83e9f",
        "date": "2022.08.06",
        "place": "Festival grounds",
        "situation": "Music festival",
        "score": 3,
        "details": "Spontaneous. The music was loud and it just made sense.",
        "observations": ""
      },
      {
        "id": "r8e94f0a",
        "date": "2022.08.07",
        "place": "Festival campsite",
        "situation": "Last night of the festival",
        "score": 3,
        "details": "",
        "observations": "Never exchanged numbers. That was fine."
      }
    ]
  },
  {
    "id": "f4x9q2m5",
    "name": "Valentina",
    "gender": "female",
    "birthYear": 2001,
    "zodiacSign": "♉ Taurus (April 20 - May 20)",
    "activity": "studies",
    "detail": "Psychology — first year",
    "howWeMet": "House party, friend of a friend",
    "birthdayAlreadyHappened": true,
    "events": [
      {
        "id": "s9f05a1b",
        "date": "2021.11.20",
        "place": "House party",
        "situation": "House party",
        "score": 2,
        "details": "",
        "observations": "We talked in the kitchen for ages. Then it happened. Never saw her again."
      }
    ]
  },
  {
    "id": "r8b3k7n2",
    "name": "Nadia",
    "gender": "female",
    "birthYear": 1998,
    "zodiacSign": "♑ Capricorn (December 22 - January 19)",
    "activity": "studies and works",
    "detail": "Part-time at a coffee shop, studying Business",
    "howWeMet": "Same workplace for a few months",
    "birthdayAlreadyHappened": true,
    "events": [
      {
        "id": "t0a16b2c",
        "date": "2022.03.12",
        "place": "Bar",
        "situation": "After-work drinks",
        "score": 3,
        "details": "",
        "observations": ""
      },
      {
        "id": "u1b27c3d",
        "date": "2022.06.24",
        "place": "Her place",
        "situation": "She invited me over after a shift",
        "score": 4,
        "details": "",
        "observations": ""
      },
      {
        "id": "v2c38d4e",
        "date": "2022.10.15",
        "place": "Park",
        "situation": "Evening walk",
        "score": 3,
        "details": "",
        "observations": "Felt easy. No pressure. Just a walk that didn't really want to end."
      },
      {
        "id": "w3d49e5f",
        "date": "2023.08.03",
        "place": "Bar",
        "situation": "Ran into her again",
        "score": 2,
        "details": "",
        "observations": "Same bar we used to go to. Some pull is just always there."
      }
    ]
  },
  {
    "id": "s5w1j4h9",
    "name": "Lena",
    "gender": "female",
    "birthYear": 1999,
    "zodiacSign": "♊ Gemini (May 21 - June 20)",
    "activity": "studies",
    "detail": "Communications — third year",
    "howWeMet": "At a music festival, she was with the same group as some friends",
    "birthdayAlreadyHappened": false,
    "events": [
      {
        "id": "x4e50f6a",
        "date": "2021.07.10",
        "place": "Festival grounds",
        "situation": "Music festival",
        "score": 4,
        "details": "We'd been dancing near each other for hours before anything happened.",
        "observations": ""
      },
      {
        "id": "y5f61a7b",
        "date": "2021.07.12",
        "place": "Festival campsite",
        "situation": "Last night of the festival",
        "score": 3,
        "details": "",
        "observations": "Said goodbye properly. We both knew there was no point trying to keep it going."
      }
    ]
  },
  {
    "id": "t3z6p8v2",
    "name": "Alex",
    "gender": "other",
    "birthYear": 1997,
    "zodiacSign": "♎ Libra (September 23 - October 22)",
    "activity": "works",
    "detail": "UX designer at a startup",
    "howWeMet": "At a queer bar, introduced by a mutual friend",
    "birthdayAlreadyHappened": false,
    "events": [
      {
        "id": "z6a72b8c",
        "date": "2021.07.10",
        "place": "Festival grounds",
        "situation": "Music festival",
        "score": 3,
        "details": "Same festival as that summer. A lot was happening that weekend.",
        "observations": ""
      },
      {
        "id": "a7b83c9d",
        "date": "2022.09.23",
        "place": "Rooftop bar",
        "situation": "Birthday rooftop gathering",
        "score": 3,
        "details": "",
        "observations": ""
      },
      {
        "id": "b8c94d0e",
        "date": "2023.11.04",
        "place": "Bar in the old quarter",
        "situation": "Random run-in, sat for hours",
        "score": 4,
        "details": "We ran into each other on the street and ended up talking until closing time.",
        "observations": "Haven't seen them since but it was one of those rare nights."
      }
    ]
  },
  {
    "id": "m7y4d1n6",
    "name": "Sara",
    "gender": "female",
    "birthYear": 2002,
    "zodiacSign": "♌ Leo (July 23 - August 23)",
    "activity": "studies",
    "detail": "Fine Arts — first year",
    "howWeMet": "At a summer festival through a common friend",
    "birthdayAlreadyHappened": false,
    "events": [
      {
        "id": "c9d05e1f",
        "date": "2023.07.22",
        "place": "Outdoor festival area",
        "situation": "Music festival",
        "score": 3,
        "details": "",
        "observations": "Brief and electric. She disappeared into the crowd. That was that."
      }
    ]
  },
  {
    "id": "q2x9f5b8",
    "name": "Marco",
    "gender": "male",
    "birthYear": 1997,
    "zodiacSign": "♐ Sagittarius (November 22 - December 21)",
    "activity": "works",
    "detail": "Personal trainer",
    "howWeMet": "Friend of a friend, same house party",
    "birthdayAlreadyHappened": false,
    "events": [
      {
        "id": "d0e16f2a",
        "date": "2021.11.20",
        "place": "House party",
        "situation": "House party",
        "score": 2,
        "details": "",
        "observations": "It was a big group, everyone was in a good mood. One of those things."
      }
    ]
  },
  {
    "id": "j6r3s1k4",
    "name": "Elena",
    "gender": "female",
    "birthYear": 2000,
    "zodiacSign": "♏ Scorpio (October 23 - November 21)",
    "activity": "studies and works",
    "detail": "Nursing student, part-time at a pharmacy",
    "howWeMet": "Through Hinge, matched and talked for weeks before meeting",
    "birthdayAlreadyHappened": false,
    "events": [
      {
        "id": "e1f27a3b",
        "date": "2022.02.19",
        "place": "Coffee shop, then her place",
        "situation": "Third date",
        "score": 4,
        "details": "Long time coming. Worth the wait.",
        "observations": ""
      },
      {
        "id": "f2a38b4c",
        "date": "2022.04.30",
        "place": "My place",
        "situation": "She cooked dinner",
        "score": 5,
        "details": "",
        "observations": ""
      },
      {
        "id": "a3b49c5d",
        "date": "2022.07.08",
        "place": "Beach",
        "situation": "Day trip, perfect sunset",
        "score": 5,
        "details": "One of those days that just works from start to finish.",
        "observations": ""
      },
      {
        "id": "b4c50d6e",
        "date": "2022.11.03",
        "place": "Her place",
        "situation": "She needed company",
        "score": 3,
        "details": "",
        "observations": "Something felt different. Like the good part might be ending."
      },
      {
        "id": "c5d61e7f",
        "date": "2023.01.20",
        "place": "My place",
        "situation": "New year, still us",
        "score": 4,
        "details": "",
        "observations": ""
      },
      {
        "id": "d6e72f8a",
        "date": "2023.05.15",
        "place": "Restaurant, then a bar",
        "situation": "Last night before she moved cities",
        "score": 3,
        "details": "",
        "observations": "We both knew. Didn't say it out loud."
      }
    ]
  },
  {
    "id": "v9n2w8t5",
    "name": "Zoe",
    "gender": "female",
    "birthYear": 1999,
    "zodiacSign": "♉ Taurus (April 20 - May 20)",
    "activity": "works",
    "detail": "Yoga instructor and content creator",
    "howWeMet": "At a music festival, we were both in the same queue",
    "birthdayAlreadyHappened": true,
    "events": [
      {
        "id": "e7f83a9b",
        "date": "2022.08.06",
        "place": "Festival grounds",
        "situation": "Music festival",
        "score": 3,
        "details": "Instant connection at the festival bar. Hours flew by.",
        "observations": ""
      },
      {
        "id": "f8a94b0c",
        "date": "2025.03.10",
        "place": "Cocktail bar downtown",
        "situation": "Reconnected after a long time",
        "score": 4,
        "details": "",
        "observations": "Almost three years and it still felt exactly the same."
      }
    ]
  },
  {
    "id": "c4m7y3h6",
    "name": "Lucas",
    "gender": "male",
    "birthYear": 1996,
    "zodiacSign": "♑ Capricorn (December 22 - January 19)",
    "activity": "works",
    "detail": "Architect at a firm",
    "howWeMet": "Old friend from high school, reconnected at a New Year's party",
    "birthdayAlreadyHappened": false,
    "events": [
      {
        "id": "a9b05c1d",
        "date": "2021.12.31",
        "place": "Rooftop NYE party",
        "situation": "New Year's Eve",
        "score": 2,
        "details": "Both a bit drunk at midnight. Old friends, new moment.",
        "observations": ""
      },
      {
        "id": "b0c16d2e",
        "date": "2022.03.05",
        "place": "Bar near his office",
        "situation": "He texted after NYE",
        "score": 3,
        "details": "",
        "observations": ""
      },
      {
        "id": "c1d27e3f",
        "date": "2022.06.18",
        "place": "Club",
        "situation": "Night out with the group",
        "score": 3,
        "details": "",
        "observations": ""
      },
      {
        "id": "d2e38f4a",
        "date": "2022.10.01",
        "place": "Rooftop bar",
        "situation": "Goodbye drinks before he moved abroad",
        "score": 4,
        "details": "Knew it was the last time. Made it count.",
        "observations": ""
      }
    ]
  },
  {
    "id": "g1p5b9z8",
    "name": "Isabelle",
    "gender": "female",
    "birthYear": 2001,
    "zodiacSign": "♓ Pisces (February 20 - March 20)",
    "activity": "studies",
    "detail": "Literature — second year",
    "howWeMet": "House party, introduced by the host",
    "birthdayAlreadyHappened": true,
    "events": [
      {
        "id": "e3f49a5b",
        "date": "2023.02.18",
        "place": "House party",
        "situation": "House party",
        "score": 2,
        "details": "We talked in a corner for hours. Then the party thinned out.",
        "observations": "She was interesting. Just never crossed paths again."
      }
    ]
  },
  {
    "id": "w8k4j2n7",
    "name": "Renata",
    "gender": "female",
    "birthYear": 1999,
    "zodiacSign": "♍ Virgo (August 24 - September 22)",
    "activity": "works",
    "detail": "Event coordinator",
    "howWeMet": "Through Instagram, she replied to a story",
    "birthdayAlreadyHappened": false,
    "events": [
      {
        "id": "f4a50b6c",
        "date": "2020.03.07",
        "place": "Her place",
        "situation": "Met in person for the first time",
        "score": 3,
        "details": "We'd been talking online for a while. Finally.",
        "observations": ""
      },
      {
        "id": "a5b61c7d",
        "date": "2020.07.14",
        "place": "Beach",
        "situation": "Summer afternoon",
        "score": 4,
        "details": "",
        "observations": "Very easy. Like we'd known each other for years."
      },
      {
        "id": "b6c72d8e",
        "date": "2020.12.01",
        "place": "Her place",
        "situation": "Quiet night in",
        "score": 3,
        "details": "",
        "observations": ""
      },
      {
        "id": "c7d83e9f",
        "date": "2021.04.22",
        "place": "Park",
        "situation": "Spring walk",
        "score": 4,
        "details": "Outdoor café first, then the park. Spring felt like an excuse for everything.",
        "observations": ""
      },
      {
        "id": "d8e94f0a",
        "date": "2021.10.30",
        "place": "Her place",
        "situation": "Halloween pre-party",
        "score": 4,
        "details": "",
        "observations": ""
      },
      {
        "id": "e9f05a1b",
        "date": "2022.09.17",
        "place": "Hotel bar",
        "situation": "She was in town for a conference",
        "score": 3,
        "details": "",
        "observations": ""
      },
      {
        "id": "f0a16b2c",
        "date": "2023.07.30",
        "place": "Her new apartment",
        "situation": "She moved, needed help, I stayed",
        "score": 3,
        "details": "",
        "observations": "Helped her unpack boxes. That's how we ended the night."
      },
      {
        "id": "a1b27c3d",
        "date": "2025.01.10",
        "place": "Bar near her place",
        "situation": "Unexpected text after a year of silence",
        "score": 2,
        "details": "",
        "observations": "Still not sure why I said yes. Then again, I always do."
      }
    ]
  },
  {
    "id": "d6t9r1v3",
    "name": "Chris",
    "gender": "male",
    "birthYear": 1998,
    "zodiacSign": "♒ Aquarius (January 20 - February 19)",
    "activity": "works",
    "detail": "Software developer",
    "howWeMet": "New Year's Eve party, same countdown spot on the rooftop",
    "birthdayAlreadyHappened": true,
    "events": [
      {
        "id": "b2c38d4e",
        "date": "2023.12.31",
        "place": "Rooftop party",
        "situation": "New Year's Eve",
        "score": 2,
        "details": "",
        "observations": ""
      },
      {
        "id": "c3d49e5f",
        "date": "2024.02.10",
        "place": "Bar",
        "situation": "He texted after NYE, wanted to meet",
        "score": 2,
        "details": "",
        "observations": "Didn't really go anywhere. Nice enough person though."
      }
    ]
  },
  {
    "id": "n3z5w7q1",
    "name": "Maya",
    "gender": "female",
    "birthYear": 2000,
    "zodiacSign": "♌ Leo (July 23 - August 23)",
    "activity": "studies",
    "detail": "Sports Science — second year",
    "howWeMet": "At the gym, kept running into each other for months",
    "birthdayAlreadyHappened": false,
    "events": [
      {
        "id": "d4e50f6a",
        "date": "2023.04.08",
        "place": "Bar",
        "situation": "After-work drinks",
        "score": 3,
        "details": "Finally got drinks after months of chatting between sets.",
        "observations": ""
      },
      {
        "id": "e5f61a7b",
        "date": "2023.06.03",
        "place": "Her place",
        "situation": "She came over to study",
        "score": 4,
        "details": "",
        "observations": "We eventually stopped studying."
      },
      {
        "id": "f6a72b8c",
        "date": "2023.09.14",
        "place": "City plaza café",
        "situation": "Last coffee before her semester abroad",
        "score": 2,
        "details": "",
        "observations": "Bittersweet. She left two days later."
      }
    ]
  },
  {
    "id": "y8j2m4b6",
    "name": "Pau",
    "gender": "female",
    "birthYear": 1997,
    "zodiacSign": "♈ Aries (March 21 - April 19)",
    "activity": "works",
    "detail": "Nurse at a public hospital",
    "howWeMet": "Through a mutual friend at a New Year's Eve party",
    "birthdayAlreadyHappened": true,
    "events": [
      {
        "id": "a7b83c9d",
        "date": "2020.12.31",
        "place": "Friend's apartment",
        "situation": "New Year's Eve",
        "score": 4,
        "details": "We'd just met that night. The countdown ended and everything changed.",
        "observations": ""
      },
      {
        "id": "b8c94d0e",
        "date": "2021.01.23",
        "place": "My place",
        "situation": "She came over after a night shift",
        "score": 4,
        "details": "",
        "observations": ""
      },
      {
        "id": "c9d05e1f",
        "date": "2021.02.20",
        "place": "Bar",
        "situation": "Night out",
        "score": 3,
        "details": "",
        "observations": ""
      },
      {
        "id": "d0e16f2a",
        "date": "2021.04.03",
        "place": "Park",
        "situation": "Her birthday walk",
        "score": 5,
        "details": "Spring afternoon. Best kiss of that whole year, honestly.",
        "observations": ""
      },
      {
        "id": "e1f27a3b",
        "date": "2021.06.12",
        "place": "Her place",
        "situation": "Last time we saw each other",
        "score": 3,
        "details": "",
        "observations": "She got complicated. We both knew it was the last time."
      }
    ]
  },
  {
    "id": "h5v7p3x9",
    "name": "Lily",
    "gender": "female",
    "birthYear": 2002,
    "zodiacSign": "♍ Virgo (August 24 - September 22)",
    "activity": "studies",
    "detail": "Pharmacy — first year",
    "howWeMet": "Through Bumble, she swiped first",
    "birthdayAlreadyHappened": false,
    "events": [
      {
        "id": "f2a38b4c",
        "date": "2024.04.27",
        "place": "Cocktail bar",
        "situation": "First date",
        "score": 3,
        "details": "Good vibe. She made me laugh a lot.",
        "observations": ""
      },
      {
        "id": "a3b49c5d",
        "date": "2024.06.15",
        "place": "Park",
        "situation": "Second date, stayed for the evening",
        "score": 4,
        "details": "",
        "observations": ""
      },
      {
        "id": "o7s9v5b3",
        "date": "2026.05.03",
        "place": "Park",
        "situation": "She reached out after almost two years",
        "score": 3,
        "details": "",
        "observations": ""
      }
    ]
  },
  {
    "id": "q1n8s6k4",
    "name": "Dante",
    "gender": "male",
    "birthYear": 1993,
    "zodiacSign": "♏ Scorpio (October 23 - November 21)",
    "activity": "works",
    "detail": "Bar manager",
    "howWeMet": "Random encounter at a bar, both waiting for friends who never showed",
    "birthdayAlreadyHappened": false,
    "events": [
      {
        "id": "b4c50d6e",
        "date": "2022.10.31",
        "place": "Bar downtown",
        "situation": "Halloween night",
        "score": 3,
        "details": "He was managing the bar. We talked all night. Friends never showed for either of us.",
        "observations": "Interesting person. Never saw him again."
      }
    ]
  },
  {
    "id": "x4b2j9m7",
    "name": "Simone",
    "gender": "female",
    "birthYear": 1999,
    "zodiacSign": "♌ Leo (July 23 - August 23)",
    "activity": "works",
    "detail": "Journalist at a local magazine",
    "howWeMet": "New Year's Eve party, same friend group",
    "birthdayAlreadyHappened": false,
    "events": [
      {
        "id": "c5d61e7f",
        "date": "2023.12.31",
        "place": "Rooftop party",
        "situation": "New Year's Eve",
        "score": 3,
        "details": "Chaotic night, great energy. Midnight made it happen.",
        "observations": ""
      },
      {
        "id": "d6e72f8a",
        "date": "2024.02.22",
        "place": "Wine bar",
        "situation": "She texted a week after NYE, wanted to meet",
        "score": 4,
        "details": "",
        "observations": ""
      },
      {
        "id": "e7f83a9b",
        "date": "2024.05.10",
        "place": "Her place",
        "situation": "She cooked dinner",
        "score": 4,
        "details": "Easy evening. She's a very comfortable person to be around.",
        "observations": ""
      },
      {
        "id": "f8a94b0c",
        "date": "2024.09.03",
        "place": "Hotel rooftop",
        "situation": "She had press passes to an event",
        "score": 4,
        "details": "Glamorous night. Completely out of my usual context.",
        "observations": ""
      },
      {
        "id": "n6r8u4a2",
        "date": "2026.04.19",
        "place": "Her place",
        "situation": "Things are becoming more regular",
        "score": 4,
        "details": "",
        "observations": ""
      }
    ]
  },
  {
    "id": "f7r5c3w1",
    "name": "Kira",
    "gender": "female",
    "birthYear": 2001,
    "zodiacSign": "♑ Capricorn (December 22 - January 19)",
    "activity": "studies",
    "detail": "Economics — third year",
    "howWeMet": "Study group, same elective",
    "birthdayAlreadyHappened": true,
    "events": [
      {
        "id": "a9b05c1d",
        "date": "2023.03.18",
        "place": "Library café",
        "situation": "Study session that went sideways",
        "score": 3,
        "details": "We were supposed to prep for an exam. Didn't.",
        "observations": ""
      },
      {
        "id": "b0c16d2e",
        "date": "2023.11.25",
        "place": "House party",
        "situation": "House party",
        "score": 3,
        "details": "",
        "observations": "Months since the library. Same spark, no explanation."
      },
      {
        "id": "c1d27e3f",
        "date": "2024.03.02",
        "place": "Bar",
        "situation": "She texted out of nowhere",
        "score": 3,
        "details": "",
        "observations": ""
      }
    ]
  },
  {
    "id": "p9z6v4h2",
    "name": "Noah",
    "gender": "male",
    "birthYear": 1998,
    "zodiacSign": "♉ Taurus (April 20 - May 20)",
    "activity": "works",
    "detail": "Music producer",
    "howWeMet": "House party, he was DJing for the night",
    "birthdayAlreadyHappened": true,
    "events": [
      {
        "id": "d2e38f4a",
        "date": "2023.02.18",
        "place": "House party",
        "situation": "House party",
        "score": 3,
        "details": "He finished his set around 1am. We found a quiet corner.",
        "observations": ""
      },
      {
        "id": "e3f49a5b",
        "date": "2023.08.20",
        "place": "Recording studio",
        "situation": "He invited me to hear something he was working on",
        "score": 3,
        "details": "",
        "observations": "Cool space. Good music. Good night."
      }
    ]
  },
  {
    "id": "t2d8n5q7",
    "name": "Bianca",
    "gender": "female",
    "birthYear": 1995,
    "zodiacSign": "♌ Leo (July 23 - August 23)",
    "activity": "works",
    "detail": "Brand strategist at an agency",
    "howWeMet": "Friend of a colleague, met at an after-work gathering",
    "birthdayAlreadyHappened": false,
    "events": [
      {
        "id": "f4a50b6c",
        "date": "2021.09.23",
        "place": "Rooftop bar",
        "situation": "After-work drinks",
        "score": 3,
        "details": "She was sharp and funny. A lot older than my usual crowd.",
        "observations": "Never followed up. Think she was with someone."
      }
    ]
  },
  {
    "id": "m6y1s9b3",
    "name": "Andrea",
    "gender": "female",
    "birthYear": 2000,
    "zodiacSign": "♎ Libra (September 23 - October 22)",
    "activity": "studies",
    "detail": "Sociology — second year",
    "howWeMet": "University, she came to an event I helped organize",
    "birthdayAlreadyHappened": false,
    "events": [
      {
        "id": "a5b61c7d",
        "date": "2021.03.25",
        "place": "University garden",
        "situation": "Evening campus event",
        "score": 3,
        "details": "Everyone else left. We kept talking.",
        "observations": ""
      },
      {
        "id": "b6c72d8e",
        "date": "2021.06.18",
        "place": "Her dorm",
        "situation": "She invited me over to study",
        "score": 4,
        "details": "",
        "observations": ""
      },
      {
        "id": "c7d83e9f",
        "date": "2021.09.11",
        "place": "Bar near campus",
        "situation": "Night out",
        "score": 3,
        "details": "Back from summer. Picked up right where we left off.",
        "observations": ""
      },
      {
        "id": "d8e94f0a",
        "date": "2022.01.29",
        "place": "Her place",
        "situation": "New semester, she invited me over",
        "score": 4,
        "details": "",
        "observations": ""
      },
      {
        "id": "e9f05a1b",
        "date": "2022.05.07",
        "place": "Park",
        "situation": "Slow spring walk",
        "score": 3,
        "details": "",
        "observations": ""
      },
      {
        "id": "f0a16b2c",
        "date": "2023.02.04",
        "place": "Café",
        "situation": "Coffee to catch up",
        "score": 1,
        "details": "",
        "observations": "She was with someone. We kept it brief. Just a hello at the door."
      }
    ]
  },
  {
    "id": "k9w4j7p5",
    "name": "Mateo",
    "gender": "male",
    "birthYear": 1996,
    "zodiacSign": "♉ Taurus (April 20 - May 20)",
    "activity": "works",
    "detail": "Physiotherapist",
    "howWeMet": "Pickup basketball game, we were on opposing teams",
    "birthdayAlreadyHappened": true,
    "events": [
      {
        "id": "a1b27c3d",
        "date": "2022.05.14",
        "place": "Sports bar",
        "situation": "After-work drinks",
        "score": 2,
        "details": "Drinks after a rematch. Unexpected.",
        "observations": ""
      },
      {
        "id": "b2c38d4e",
        "date": "2022.07.30",
        "place": "Club",
        "situation": "Night out",
        "score": 2,
        "details": "",
        "observations": ""
      },
      {
        "id": "c3d49e5f",
        "date": "2022.12.10",
        "place": "His place",
        "situation": "Holiday gathering at his flat",
        "score": 3,
        "details": "",
        "observations": "Good group of people. He pulled me aside near the end of the night."
      }
    ]
  },
  {
    "id": "z3h6t1n8",
    "name": "Ines",
    "gender": "female",
    "birthYear": 1999,
    "zodiacSign": "♐ Sagittarius (November 22 - December 21)",
    "activity": "studies and works",
    "detail": "Law student, intern at a firm",
    "howWeMet": "House party, she was a friend of the host's partner",
    "birthdayAlreadyHappened": false,
    "events": [
      {
        "id": "d4e50f6a",
        "date": "2023.02.18",
        "place": "House party",
        "situation": "House party",
        "score": 3,
        "details": "Intense conversation. She was interesting in a way that caught me off guard.",
        "observations": ""
      },
      {
        "id": "e5f61a7b",
        "date": "2023.10.14",
        "place": "Rooftop bar",
        "situation": "She texted months later",
        "score": 4,
        "details": "",
        "observations": "Same pull as that night in February. Some things don't need explaining."
      }
    ]
  },
  {
    "id": "v7x2m5r4",
    "name": "Cleo",
    "gender": "other",
    "birthYear": 2000,
    "zodiacSign": "♒ Aquarius (January 20 - February 19)",
    "activity": "works",
    "detail": "Tattoo artist",
    "howWeMet": "At an exhibition opening, we were both staring at the same piece",
    "birthdayAlreadyHappened": true,
    "events": [
      {
        "id": "f6a72b8c",
        "date": "2022.04.16",
        "place": "Gallery bar",
        "situation": "After the exhibition opening",
        "score": 4,
        "details": "We left together before the show ended. Neither of us mentioned it.",
        "observations": ""
      },
      {
        "id": "a7b83c9d",
        "date": "2022.11.19",
        "place": "Their studio",
        "situation": "Went in for a tattoo consult",
        "score": 3,
        "details": "",
        "observations": "Left with a design appointment and something else too."
      },
      {
        "id": "b8c94d0e",
        "date": "2023.06.24",
        "place": "Bar",
        "situation": "Summer night, same place as always",
        "score": 3,
        "details": "",
        "observations": ""
      },
      {
        "id": "c9d05e1f",
        "date": "2024.01.12",
        "place": "Their place",
        "situation": "They texted first, new year energy",
        "score": 4,
        "details": "",
        "observations": ""
      }
    ]
  },
  {
    "id": "b1n9q6k3",
    "name": "Vera",
    "gender": "female",
    "birthYear": 1997,
    "zodiacSign": "♎ Libra (September 23 - October 22)",
    "activity": "works",
    "detail": "Primary school teacher",
    "howWeMet": "At a summer festival, near the same stage",
    "birthdayAlreadyHappened": false,
    "events": [
      {
        "id": "d0e16f2a",
        "date": "2023.07.22",
        "place": "Outdoor festival area",
        "situation": "Music festival",
        "score": 3,
        "details": "Brief but memorable. She was fully in the moment.",
        "observations": "Never got her number. Didn't feel like the right thing to do."
      }
    ]
  },
  {
    "id": "s8z4w7d2",
    "name": "Remi",
    "gender": "female",
    "birthYear": 1998,
    "zodiacSign": "♍ Virgo (August 24 - September 22)",
    "activity": "works",
    "detail": "Copywriter and illustrator",
    "howWeMet": "Through Tinder, we texted for weeks before actually meeting",
    "birthdayAlreadyHappened": false,
    "events": [
      {
        "id": "e1f27a3b",
        "date": "2020.05.16",
        "place": "Park, then my place",
        "situation": "Finally met after weeks of talking",
        "score": 4,
        "details": "Walk in the park first. Neither of us wanted it to end.",
        "observations": ""
      },
      {
        "id": "f2a38b4c",
        "date": "2020.09.12",
        "place": "Her place",
        "situation": "End of summer, one more time",
        "score": 3,
        "details": "",
        "observations": ""
      },
      {
        "id": "a3b49c5d",
        "date": "2021.03.14",
        "place": "Bar",
        "situation": "She texted after months of silence",
        "score": 3,
        "details": "",
        "observations": "Couldn't say no. Never can."
      },
      {
        "id": "b4c50d6e",
        "date": "2021.11.07",
        "place": "My place",
        "situation": "Late night, she just showed up",
        "score": 4,
        "details": "",
        "observations": "Back again. Always back again."
      },
      {
        "id": "c5d61e7f",
        "date": "2022.06.11",
        "place": "Her place",
        "situation": "She moved, invited me to see the new flat",
        "score": 4,
        "details": "",
        "observations": ""
      },
      {
        "id": "d6e72f8a",
        "date": "2023.02.28",
        "place": "Bar",
        "situation": "3am text in February",
        "score": 3,
        "details": "",
        "observations": "Cold season ritual at this point."
      },
      {
        "id": "e7f83a9b",
        "date": "2023.10.20",
        "place": "Concert venue",
        "situation": "She had a spare ticket",
        "score": 4,
        "details": "Great band. We barely watched the second half.",
        "observations": ""
      },
      {
        "id": "f8a94b0c",
        "date": "2024.07.04",
        "place": "Her place",
        "situation": "We keep finding our way back",
        "score": 4,
        "details": "",
        "observations": ""
      },
      {
        "id": "a9b05c1d",
        "date": "2025.09.22",
        "place": "My place",
        "situation": "Years later and nothing's really changed",
        "score": 3,
        "details": "",
        "observations": "Didn't even try to explain it. We just don't."
      },
      {
        "id": "m5q7t3z1",
        "date": "2026.02.14",
        "place": "Her place",
        "situation": "Valentine's Day text at midnight",
        "score": 3,
        "details": "",
        "observations": "Of course she did. Of course I went."
      }
    ]
  },
  {
    "id": "j5p3b1y9",
    "name": "Oscar",
    "gender": "male",
    "birthYear": 1994,
    "zodiacSign": "♏ Scorpio (October 23 - November 21)",
    "activity": "works",
    "detail": "Documentary filmmaker",
    "howWeMet": "At a gallery opening, friend of a friend",
    "birthdayAlreadyHappened": false,
    "events": [
      {
        "id": "b0c16d2e",
        "date": "2023.04.29",
        "place": "Bar after the gallery",
        "situation": "End of the night, impulsive",
        "score": 2,
        "details": "",
        "observations": "He seemed surprised. So was I."
      }
    ]
  },
  {
    "id": "r6m8n4v7",
    "name": "Talia",
    "gender": "female",
    "birthYear": 2003,
    "zodiacSign": "♋ Cancer (June 21 - July 22)",
    "activity": "studies",
    "detail": "Biology — first year",
    "howWeMet": "Through Hinge, she messaged first",
    "birthdayAlreadyHappened": false,
    "events": [
      {
        "id": "c1d27e3f",
        "date": "2024.05.18",
        "place": "Park",
        "situation": "First meet, afternoon walk",
        "score": 3,
        "details": "She suggested the park. Good call. Very easy conversation.",
        "observations": ""
      },
      {
        "id": "d2e38f4a",
        "date": "2024.07.19",
        "place": "Concert venue",
        "situation": "She got tickets to a show",
        "score": 4,
        "details": "",
        "observations": ""
      }
    ]
  },
  {
    "id": "g4k1z9s6",
    "name": "Nat",
    "gender": "female",
    "birthYear": 1999,
    "zodiacSign": "♑ Capricorn (December 22 - January 19)",
    "activity": "works",
    "detail": "Product manager at a tech startup",
    "howWeMet": "Work conference, both stuck at the same panel",
    "birthdayAlreadyHappened": false,
    "events": [
      {
        "id": "e3f49a5b",
        "date": "2023.09.30",
        "place": "Conference bar",
        "situation": "After the panel, drinks that went long",
        "score": 3,
        "details": "We stayed talking until the bar closed.",
        "observations": ""
      },
      {
        "id": "f4a50b6c",
        "date": "2024.04.13",
        "place": "My place",
        "situation": "She was in town for work",
        "score": 4,
        "details": "",
        "observations": ""
      },
      {
        "id": "a5b61c7d",
        "date": "2025.06.07",
        "place": "Rooftop bar",
        "situation": "She moved to the city, felt right to try something",
        "score": 4,
        "details": "Nice to have things feel like more than a passing thing for once.",
        "observations": ""
      }
    ]
  },
  {
    "id": "s1w3z9f7",
    "name": "Lucie",
    "gender": "female",
    "birthYear": 1997,
    "zodiacSign": "♓ Pisces (February 20 - March 20)",
    "activity": "studies",
    "detail": "Fine Arts — third year",
    "howWeMet": "Met through a mutual friend while visiting another city that summer",
    "birthdayAlreadyHappened": true,
    "events": [
      {
        "id": "p8t0w6c4",
        "date": "2019.04.20",
        "place": "Art school bar",
        "situation": "After a student exhibition",
        "score": 3,
        "details": "I was visiting for a few weeks. She was showing her work. We ended up closing the bar.",
        "observations": ""
      },
      {
        "id": "q9u1x7d5",
        "date": "2019.05.18",
        "place": "Park",
        "situation": "She offered to show me around the city",
        "score": 4,
        "details": "",
        "observations": ""
      },
      {
        "id": "r0v2y8e6",
        "date": "2019.07.05",
        "place": "Bar",
        "situation": "Last night before I left",
        "score": 4,
        "details": "",
        "observations": "We didn't exchange numbers. It felt like the right way to leave it."
      }
    ]
  }
]
